tests/BaseRunner.py
tests/__init__.py
tests/performance_test.py
tests/test_aistats.py
tests/test_atc.py
tests/test_ccgrid.py
tests/test_ccpe.py
tests/test_cloud.py
tests/test_cloudcom.py
tests/test_cloudcomp.py
tests/test_cluster.py
tests/test_cvpr.py
tests/test_dsn.py
tests/test_edbt.py
tests/test_escience.py
tests/test_europar.py
tests/test_eurosys.py
tests/test_fast.py
tests/test_fedcsis.py
tests/test_fgcs.py
tests/test_ficloud.py
tests/test_gcc.py
tests/test_grid.py
tests/test_hipc.py
tests/test_hotcloud.py
tests/test_hpcc.py
tests/test_hpdc.py
tests/test_ibmrd.py
tests/test_ic.py
tests/test_ic2e.py
tests/test_icac.py
tests/test_iccse.py
tests/test_icdcs.py
tests/test_icfec.py
tests/test_icpe.py
tests/test_icpp.py
tests/test_icws.py
tests/test_ijhpca.py
tests/test_imc.py
tests/test_infocom.py
tests/test_ipdps.py
tests/test_isc.py
tests/test_iscid.py
tests/test_ispa.py
tests/test_ispdc.py
tests/test_iswc.py
tests/test_jidps.py
tests/test_jpdc.py
tests/test_jsspp.py
tests/test_mobilesoft.py
tests/test_ndss.py
tests/test_nossdav.py
tests/test_nsdi.py
tests/test_osdi.py
tests/test_p2p.py
tests/test_pc.py
tests/test_pods.py
tests/test_popl.py
tests/test_ppopp.py
tests/test_psi.py
tests/test_saso.py
tests/test_sc.py
tests/test_services.py
tests/test_sigcomm.py
tests/test_sigcse.py
tests/test_sigmetrics.py
tests/test_sigmod.py
tests/test_socc.py
tests/test_sosp.py
tests/test_spire.py
tests/test_spw.py
tests/test_ssdbm.py
tests/test_systor.py
tests/test_tc.py
tests/test_tjs.py
tests/test_tompecs.py
tests/test_toplas.py
tests/test_tpds.py
tests/test_true_negatives.py
tests/test_ucc.py
tests/test_works.py
tests/test_wowmom.py
venue_mapper/__init__.py
venue_mapper/venue_mapper.py
Venue_Mapper-1.0.2.dist-info/LICENSE
Venue_Mapper-1.0.2.dist-info/METADATA
Venue_Mapper-1.0.2.dist-info/WHEEL
Venue_Mapper-1.0.2.dist-info/top_level.txt
Venue_Mapper-1.0.2.dist-info/RECORD
