Metadata-Version: 2.1
Name: Venue Mapper
Version: 1.0.2
Summary: Maps BibTex venue/journal/booktitle strings to their acronyms.
Home-page: https://github.com/atlarge-research/venue_mappings
Author: Laurens Versluis
Author-email: l.f.d.versluis@vu.nl
License: UNKNOWN
Platform: UNKNOWN
Classifier: Programming Language :: Python :: 3
Classifier: Operating System :: OS Independent
Requires-Python: >=3.5
License-File: LICENSE
